{
  "root": true,
  "project": {
    "name": "nervous-yam-d2c76"
  },
  "api": {
    "projectId": "seooebtm",
    "dataset": "production"
  },
  "plugins": [
    "@sanity/base",
    "@sanity/components",
    "@sanity/default-layout",
    "@sanity/default-login",
    "@sanity/desk-tool",
    "markdown",
    "@sanity/color-input"
  ],
  "parts": [
    {
      "name": "part:@sanity/base/schema",
      "path": "./schemas/schema.js"
    },
    {
      "name": "part:@sanity/desk-tool/structure",
      "path": "./deskStructure.js"
    }
  ]
}
